.gitignore
.pre-commit-config.yaml
LICENSE
MANIFEST.in
README.html
README.md
mkdocs.yml
setup.cfg
setup.py
tox.ini
.github/workflows/test_and_deploy.yml
.napari/DESCRIPTION.html
.napari/DESCRIPTION.md
docs/ESI.png
docs/ESI_Original_donuts.png
docs/ESI_Processed_nrResImage_1_nrBins_2_esi_order_1_donuts.png
docs/Fig_2a_MSSR_Garcia_2021.png
docs/Fig_6_ESI_Alva_2022.png
docs/Fig_7_SRRF_Alva_2022.png
docs/MSSR.png
docs/MSSR_Processed_amp_2_PSFp_1_order_1_raw7_100_donuts.png
docs/MSSR_original_donuts.png
docs/MUSICAL-CardioMyoblast_Mitochondria.png
docs/SOFI.png
docs/SRRF.png
docs/SRRF_Original_Microtubules.png
docs/SRRF_processed_mag_2_rad_3_symAxis_3_fstart_0_fend_3_Microtubules.png
docs/TMSSR.png
docs/index.md
docs/musical_mean.png
docs/noMSSR.png
docs/noSOFI.png
docs/single-frame-good-exposure.png
docs/single-frame-good-exposure.tif
docs/synt.png
docs/tmssr-mean-mag2.png
src/napari_superres/__init__.py
src/napari_superres/_gui_creator.py
src/napari_superres/_reader.py
src/napari_superres/_version.py
src/napari_superres/_writer.py
src/napari_superres/core_decor.py
src/napari_superres/core_esi.py
src/napari_superres/core_mssr.py
src/napari_superres/core_mssr_numba.py
src/napari_superres/core_musical.py
src/napari_superres/core_sofi.py
src/napari_superres/core_srrf.py
src/napari_superres/deconvsk.py
src/napari_superres/finterp.py
src/napari_superres/my_popW.py
src/napari_superres/napari.yaml
src/napari_superres.egg-info/PKG-INFO
src/napari_superres.egg-info/SOURCES.txt
src/napari_superres.egg-info/dependency_links.txt
src/napari_superres.egg-info/entry_points.txt
src/napari_superres.egg-info/requires.txt
src/napari_superres.egg-info/top_level.txt
src/napari_superres/_tests/__init__.py
src/napari_superres/_tests/test_reader.py
src/napari_superres/_tests/test_widget.py
src/napari_superres/_tests/test_writer.py