Metadata-Version: 2.1
Name: napari-superres
Version: 0.1.1
Summary: Fluorescence Fluctuation-based Super Resolution (FF-SRM) Methods
Home-page: https://github.com/RoccoDAnt/napari-superres
Author: "Rocco D'Antuono, Adán Guerrero, Raúl Pinto Cámara, Paúl Hernández Herrera, Esley Torres Garcia, Haydee Hernández, Julián Mejía"
Author-email: rocco.dantuono@hotmail.it
License: BSD-3-Clause
Project-URL: Bug Tracker, https://github.com/RoccoDAnt/napari-superres/issues
Project-URL: Documentation, https://github.com/RoccoDAnt/napari-superres#README.md
Project-URL: Source Code, https://github.com/RoccoDAnt/napari-superres
Project-URL: User Support, https://github.com/RoccoDAnt/napari-superres/issues
Classifier: Development Status :: 2 - Pre-Alpha
Classifier: Framework :: napari
Classifier: Intended Audience :: Developers
Classifier: License :: OSI Approved :: BSD License
Classifier: Operating System :: OS Independent
Classifier: Programming Language :: Python
Classifier: Programming Language :: Python :: 3
Classifier: Programming Language :: Python :: 3 :: Only
Classifier: Programming Language :: Python :: 3.8
Classifier: Programming Language :: Python :: 3.9
Classifier: Programming Language :: Python :: 3.10
Classifier: Topic :: Scientific/Engineering :: Image Processing
Requires-Python: >=3.8
Provides-Extra: testing
License-File: LICENSE
